batch_traceability/__init__.py
batch_traceability/cli.py
batch_traceability/recall.py
batch_traceability/traceability.py
batch_traceability_mock_recall-0.1.1.dist-info/licenses/LICENSE
batch_traceability_mock_recall-0.1.1.dist-info/METADATA
batch_traceability_mock_recall-0.1.1.dist-info/WHEEL
batch_traceability_mock_recall-0.1.1.dist-info/entry_points.txt
batch_traceability_mock_recall-0.1.1.dist-info/top_level.txt
batch_traceability_mock_recall-0.1.1.dist-info/RECORD
