Metadata-Version: 2.4
Name: batch-traceability-mock-recall
Version: 0.1.1
Summary: Batch traceability and mock recall CLI tool (one step back / one step forward)
Author: Federico
License: MIT
Requires-Python: >=3.10
License-File: LICENSE
Requires-Dist: pandas
Dynamic: license-file
